{
  "project_info": {
    "project_number": "943853159779",
    "project_id": "run-with-zippy-aef9a",
    "storage_bucket": "run-with-zippy-aef9a.appspot.com"
  },
  "client": [
    {
      "client_info": {
        "mobilesdk_app_id": "1:943853159779:android:846614c7ef744cc25a3f56",
        "android_client_info": {
          "package_name": "com.rungo.runwithzippy"
        }
      },
      "oauth_client": [
        {
          "client_id": "943853159779-l6uti2nfql8kj5ul1fvbuebil45bbppk.apps.googleusercontent.com",
          "client_type": 1,
          "android_info": {
            "package_name": "com.rungo.runwithzippy",
            "certificate_hash": "3bace823f3a67ace2165ada77c379319d860003f"
          }
        },
        {
          "client_id": "943853159779-8ql3ru85d247pdbplfdh45u28a8ndp8n.apps.googleusercontent.com",
          "client_type": 3
        }
      ],
      "api_key": [
        {
          "current_key": "AIzaSyDGEnJHXzgi6UXlD4NoIR9El_dIcEHQJ-0"
        }
      ],
      "services": {
        "appinvite_service": {
          "other_platform_oauth_client": [
            {
              "client_id": "943853159779-8ql3ru85d247pdbplfdh45u28a8ndp8n.apps.googleusercontent.com",
              "client_type": 3
            },
            {
              "client_id": "943853159779-3a5bgcmddo6lhauhmj7pag8pj7nrmfke.apps.googleusercontent.com",
              "client_type": 2,
              "ios_info": {
                "bundle_id": "com.myrungo.ios-app1"
              }
            }
          ]
        }
      }
    }
  ],
  "configuration_version": "1"
}